emoji_magic.py
setup.cfg
setup.py
emoji_ipython_magic.egg-info/PKG-INFO
emoji_ipython_magic.egg-info/SOURCES.txt
emoji_ipython_magic.egg-info/dependency_links.txt
emoji_ipython_magic.egg-info/requires.txt
emoji_ipython_magic.egg-info/top_level.txt