Metadata-Version: 1.1
Name: emoji-ipython-magic
Version: 0.0.1
Summary: emoji magic for IPython 3
Home-page: https://github.com/AustinRochford/emoji-ipython-magic
Author: Austin Rochford
Author-email: austin.rochford@gmail.com
License: MIT
Keywords: ipython
Platform: any
Classifier: Development Status :: 4 - Beta
Classifier: Intended Audience :: Developers
Classifier: Operating System :: OS Independent
Classifier: Programming Language :: Python
